viconfig/Config.py
viconfig/FType.py
viconfig/Field.py
viconfig/__init__.py
viconfig-0.0.2.dist-info/licenses/LICENSE.txt
viconfig-0.0.2.dist-info/METADATA
viconfig-0.0.2.dist-info/WHEEL
viconfig-0.0.2.dist-info/top_level.txt
viconfig-0.0.2.dist-info/RECORD
