Metadata-Version: 2.4
Name: viconfig
Version: 0.0.2
Summary: 带数据验证的服务器配置信息库
Author-email: zhoubinzyb <2314910401@qq.com>
License-Expression: MIT AND (Apache-2.0 OR BSD-2-Clause)
Keywords: 服务器配置信息
Classifier: Development Status :: 3 - Alpha
Classifier: Intended Audience :: Developers
Classifier: Topic :: Software Development :: Build Tools
Classifier: Programming Language :: Python :: 3.8
Classifier: Programming Language :: Python :: 3.9
Classifier: Programming Language :: Python :: 3.10
Classifier: Programming Language :: Python :: 3.11
Requires-Python: >=3.8
License-File: LICENSE.txt
Requires-Dist: pathlib
Dynamic: license-file
